jms/__init__.py
jms/coverage.py
jms/dbStructures.py
jms/empiricalCpds.py
jms/formula.py
jms/io.py
jms/ions.py
jms/modelConvert.py
jms/model_port.py
jms/search.py
jms/test.py
jms/updates.py
jms/data/__init__.py
jms/data/humangem_pathways.py
jms/data/list_formula_mass.py
jms/data/masters.py
jms/data/smpdb_pathways.py
jms/utils/Tabular2Json.py
jms/utils/__init__.py
jms/utils/chemebi.py
jms/utils/gems.py
jms/utils/hmdb.py
jms/utils/pubchem.py
jms/utils/refmet.py
jms_metabolite_services-0.5.8.dist-info/LICENSE
jms_metabolite_services-0.5.8.dist-info/METADATA
jms_metabolite_services-0.5.8.dist-info/WHEEL
jms_metabolite_services-0.5.8.dist-info/top_level.txt
jms_metabolite_services-0.5.8.dist-info/RECORD
