Metadata-Version: 2.1
Name: jms-metabolite-services
Version: 0.5.8
Summary: conversion, search of metabolic models and metabolomics data
Home-page: https://github.com/shuzhao-li/JMS
Author: Shuzhao Li, Minghao Gong
Author-email: shuzhao.li@gmail.com
License: Python
Keywords: metabolomics,chemistry,bioinformatics,mass spectrometry
Classifier: Development Status :: 4 - Beta
Classifier: Intended Audience :: Developers
Classifier: Intended Audience :: Science/Research
Classifier: License :: OSI Approved :: BSD License
Classifier: Natural Language :: English
Classifier: Operating System :: OS Independent
Classifier: Programming Language :: Python :: 3.7
Classifier: Topic :: Scientific/Engineering :: Bio-Informatics
Classifier: Topic :: Software Development :: Libraries :: Python Modules
Requires-Python: >=3
License-File: LICENSE
Requires-Dist: mass2chem
